kubeasy-sdk/__init__.py
kubeasy-sdk/container.py
kubeasy-sdk/deployment.py
kubeasy-sdk/ingress.py
kubeasy-sdk/service.py
kubeasy-sdk/volume.py
kubeasy_builder/__init__.py
kubeasy_builder/build.py
kubeasy_sdk/__init__.py
kubeasy_sdk/container.py
kubeasy_sdk/deployment.py
kubeasy_sdk/ingress.py
kubeasy_sdk/service.py
kubeasy_sdk/volume.py
kubeasy_sdk/utils/__init__.py
kubeasy_sdk/utils/request_limits.py
kubeasy_sdk/utils/resource.py
kubeasy_sdk/utils/security.py
kubeasy_sdk/utils/collections/__init__.py
kubeasy_sdk/utils/collections/chart_resource_collection.py
kubeasy_sdk/utils/collections/container_ports.py
kubeasy_sdk/utils/collections/containers.py
kubeasy_sdk/utils/collections/service_ports.py
kubeasy_sdk/utils/collections/volumes.py
kubeasy_sdk/utils/networking/__init__.py
kubeasy_sdk/utils/networking/container_port.py
kubeasy_sdk/utils/networking/service_port.py
kubeasy_server/__init__.py
kubeasy_server/run.py
kubeasy_sdk-0.1.24.dist-info/LICENSE.txt
kubeasy_sdk-0.1.24.dist-info/METADATA
kubeasy_sdk-0.1.24.dist-info/WHEEL
kubeasy_sdk-0.1.24.dist-info/top_level.txt
kubeasy_sdk-0.1.24.dist-info/RECORD
